{
    "809495637569306684": {
        "username": "kingxcampbell",
        "points": 390,
        "points_today": 390,
        "level": 1,
        "messages_sent": 29,
        "characters_typed": 225,
        "minutes_in_voice": 0,
        "minutes_online": 627,
        "voice_activations": 0,
        "total_talking_time": 0,
        "coins": 500
    },
    "1170556246257057888": {
        "username": "jonnyboyballa",
        "points": 18800,
        "points_today": 18800,
        "level": 1,
        "messages_sent": 949,
        "characters_typed": 12645,
        "minutes_in_voice": 0,
        "minutes_online": 2055,
        "voice_activations": 0,
        "total_talking_time": 0,
        "coins": 96,
        "last_daily": "2024-07-11 15:54:33"
    },
    "443232925769531392": {
        "username": "dommyduke",
        "points": 4440,
        "points_today": 4440,
        "level": 1,
        "messages_sent": 294,
        "characters_typed": 2613,
        "minutes_in_voice": 0,
        "minutes_online": 582,
        "voice_activations": 0,
        "total_talking_time": 0,
        "coins": 814,
        "last_daily": "2024-07-11 15:08:08"
    },
    "711995446020669450": {
        "username": "tyman0099",
        "points": 0,
        "points_today": 0,
        "level": 1,
        "messages_sent": 0,
        "characters_typed": 0,
        "minutes_in_voice": 0,
        "minutes_online": 586,
        "voice_activations": 0,
        "total_talking_time": 0,
        "coins": 0
    },
    "462165652719927318": {
        "username": "sortinhat",
        "points": 2560,
        "points_today": 2560,
        "level": 1,
        "messages_sent": 196,
        "characters_typed": 2861,
        "minutes_in_voice": 0,
        "minutes_online": 628,
        "voice_activations": 0,
        "total_talking_time": 0,
        "coins": 9883,
        "last_daily": "2024-07-11 18:13:03"
    },
    "564435147840028682": {
        "username": "northcaught",
        "points": 0,
        "points_today": 0,
        "level": 1,
        "messages_sent": 0,
        "characters_typed": 0,
        "minutes_in_voice": 0,
        "minutes_online": 432,
        "voice_activations": 0,
        "total_talking_time": 0,
        "coins": 0
    },
    "704523517676224524": {
        "username": "beameclipse",
        "points": 0,
        "points_today": 0,
        "level": 1,
        "messages_sent": 0,
        "characters_typed": 0,
        "minutes_in_voice": 0,
        "minutes_online": 430,
        "voice_activations": 0,
        "total_talking_time": 0,
        "coins": 0
    },
    "745818677429010464": {
        "username": "ljdaballa",
        "points": 0,
        "points_today": 0,
        "level": 1,
        "messages_sent": 0,
        "characters_typed": 0,
        "minutes_in_voice": 0,
        "minutes_online": 220,
        "voice_activations": 0,
        "total_talking_time": 0,
        "coins": 0
    },
    "998746425301143653": {
        "username": "wolfishtuna.",
        "points": 0,
        "points_today": 0,
        "level": 1,
        "messages_sent": 0,
        "characters_typed": 0,
        "minutes_in_voice": 0,
        "minutes_online": 220,
        "voice_activations": 0,
        "total_talking_time": 0,
        "coins": 0
    },
    "530477499998666753": {
        "username": "tuck_boon",
        "points": 1030,
        "points_today": 1030,
        "level": 1,
        "messages_sent": 103,
        "characters_typed": 971,
        "minutes_in_voice": 0,
        "minutes_online": 256,
        "voice_activations": 0,
        "total_talking_time": 0,
        "coins": 5778,
        "last_daily": "2024-07-12 00:50:27"
    },
    "624678686980833312": {
        "username": "devivomario",
        "points": 1570,
        "points_today": 1570,
        "level": 1,
        "messages_sent": 87,
        "characters_typed": 585,
        "minutes_in_voice": 0,
        "minutes_online": 492,
        "voice_activations": 0,
        "total_talking_time": 0,
        "coins": 0,
        "last_daily": "2024-07-12 01:05:43"
    },
    "414909253623611413": {
        "username": "earlxo",
        "points": 0,
        "points_today": 0,
        "level": 1,
        "messages_sent": 0,
        "characters_typed": 0,
        "minutes_in_voice": 0,
        "minutes_online": 298,
        "voice_activations": 0,
        "total_talking_time": 0,
        "coins": 0
    },
    "331868414580752396": {
        "username": "gracevanderwaal_",
        "points": 20,
        "points_today": 20,
        "level": 1,
        "messages_sent": 2,
        "characters_typed": 49,
        "minutes_in_voice": 0,
        "minutes_online": 438,
        "voice_activations": 0,
        "total_talking_time": 0,
        "coins": 0
    },
    "517136591903391755": {
        "username": "itzjuzo",
        "points": 10,
        "points_today": 10,
        "level": 1,
        "messages_sent": 1,
        "characters_typed": 4,
        "minutes_in_voice": 0,
        "minutes_online": 470,
        "voice_activations": 0,
        "total_talking_time": 0,
        "coins": 0
    },
    "1069318870906720266": {
        "username": "esarv.",
        "points": 30,
        "points_today": 30,
        "level": 1,
        "messages_sent": 3,
        "characters_typed": 35,
        "minutes_in_voice": 0,
        "minutes_online": 66,
        "voice_activations": 0,
        "total_talking_time": 0,
        "coins": 0
    },
    "292441451516919811": {
        "username": "boosh51",
        "points": 40,
        "points_today": 40,
        "level": 1,
        "messages_sent": 4,
        "characters_typed": 155,
        "minutes_in_voice": 0,
        "minutes_online": 0,
        "voice_activations": 0,
        "total_talking_time": 0,
        "coins": 0
    },
    "727228028081406032": {
        "username": "rashaunbrown42",
        "points": 0,
        "points_today": 0,
        "level": 1,
        "messages_sent": 0,
        "characters_typed": 0,
        "minutes_in_voice": 0,
        "minutes_online": 40,
        "voice_activations": 0,
        "total_talking_time": 0,
        "coins": 0
    },
    "1257139754546237461": {
        "username": "nathanh24.",
        "points": 440,
        "points_today": 440,
        "level": 1,
        "messages_sent": 44,
        "characters_typed": 299,
        "minutes_in_voice": 0,
        "minutes_online": 34,
        "voice_activations": 0,
        "total_talking_time": 0,
        "coins": 0
    }
}